demo_jupyter_wasm_widget/__init__.py
demo_jupyter_wasm_widget/widget.py
demo_jupyter_wasm_widget/static/wgpu_app.wasm
demo_jupyter_wasm_widget/static/widget.js
demo_jupyter_wasm_widget-0.1.0.dev0.dist-info/METADATA
demo_jupyter_wasm_widget-0.1.0.dev0.dist-info/WHEEL
demo_jupyter_wasm_widget-0.1.0.dev0.dist-info/licenses/LICENSE.md
demo_jupyter_wasm_widget-0.1.0.dev0.dist-info/RECORD
